tscli/__init__.py
tscli/packer.py
tscli/secure_operate_pb2.py
tscli/secure_operate_pb2_grpc.py
tscli/version.py
tscli-0.0.3.dist-info/METADATA
tscli-0.0.3.dist-info/WHEEL
tscli-0.0.3.dist-info/top_level.txt
tscli-0.0.3.dist-info/RECORD
