Metadata-Version: 2.1
Name: tscli
Version: 0.0.3
Summary: A client library for call tensor-serving
Home-page: UNKNOWN
Author: dachui
Author-email: dazhu.wang@trustbe.net
License: Trustbe
Keywords: Tensor Serving Client SDK
Platform: UNKNOWN
Classifier: Programming Language :: Python :: 3
Classifier: Operating System :: OS Independent
Requires-Dist: grpcio
